odoo10_addon_purchase_cancel_reason-10.0.1.0.0-py2.7-nspkg.pth
odoo/addons/purchase_cancel_reason/README.rst
odoo/addons/purchase_cancel_reason/__init__.py
odoo/addons/purchase_cancel_reason/__manifest__.py
odoo/addons/purchase_cancel_reason/data/purchase_order_cancel_reason.xml
odoo/addons/purchase_cancel_reason/i18n/fr_BE.po
odoo/addons/purchase_cancel_reason/i18n/purchase_cancel_reason.pot
odoo/addons/purchase_cancel_reason/model/__init__.py
odoo/addons/purchase_cancel_reason/model/purchase_order.py
odoo/addons/purchase_cancel_reason/security/ir.model.access.csv
odoo/addons/purchase_cancel_reason/static/description/icon.png
odoo/addons/purchase_cancel_reason/tests/__init__.py
odoo/addons/purchase_cancel_reason/tests/test_purchase_cancel_reason.py
odoo/addons/purchase_cancel_reason/views/purchase_order.xml
odoo/addons/purchase_cancel_reason/wizard/__init__.py
odoo/addons/purchase_cancel_reason/wizard/purchase_cancel_reason.py
odoo/addons/purchase_cancel_reason/wizard/purchase_cancel_reason_view.xml
odoo10_addon_purchase_cancel_reason-10.0.1.0.0.dist-info/DESCRIPTION.rst
odoo10_addon_purchase_cancel_reason-10.0.1.0.0.dist-info/METADATA
odoo10_addon_purchase_cancel_reason-10.0.1.0.0.dist-info/RECORD
odoo10_addon_purchase_cancel_reason-10.0.1.0.0.dist-info/WHEEL
odoo10_addon_purchase_cancel_reason-10.0.1.0.0.dist-info/metadata.json
odoo10_addon_purchase_cancel_reason-10.0.1.0.0.dist-info/namespace_packages.txt
odoo10_addon_purchase_cancel_reason-10.0.1.0.0.dist-info/top_level.txt
