Metadata-Version: 2.0
Name: odoo10-addon-purchase-cancel-reason
Version: 10.0.1.0.0
Summary: Purchase Cancel Reason
Home-page: https://github.com/OCA/purchase-workflow
Author: Camptocamp,Odoo Community Association (OCA), Okia SPRL
Author-email: support@odoo-community.org
License: AGPL-3
Platform: UNKNOWN
Classifier: Programming Language :: Python
Classifier: Framework :: Odoo
Classifier: License :: OSI Approved :: GNU Affero General Public License v3
Requires-Python: ~=2.7
Requires-Dist: odoo (<10.1dev,>=10.0)
